pairwisedist/__init__.py
pairwisedist/pairwisedist.py
tests/.coverage
tests/__init__.py
tests/coverage.xml
tests/test_pairwisedist.py
tests/.pytest_cache/.gitignore
tests/.pytest_cache/CACHEDIR.TAG
tests/.pytest_cache/README.md
tests/.pytest_cache/v/cache/lastfailed
tests/.pytest_cache/v/cache/nodeids
tests/.pytest_cache/v/cache/stepwise
pairwisedist-1.3.1.dist-info/AUTHORS.rst
pairwisedist-1.3.1.dist-info/LICENSE
pairwisedist-1.3.1.dist-info/METADATA
pairwisedist-1.3.1.dist-info/WHEEL
pairwisedist-1.3.1.dist-info/top_level.txt
pairwisedist-1.3.1.dist-info/RECORD
