Metadata-Version: 2.1
Name: pairwisedist
Version: 1.3.1
Summary: Calculate the pairwise-distance matrix for an array of *n* samples by *p* features, sing a selection of distance metrics.
Home-page: https://github.com/GuyTeichman/pairwisedist
Author: Guy Teichman
Author-email: guyteichman@gmail.com
License: License :: OSI Approved :: Apache Software License
Keywords: distance,pairwise distance,YS1,YR1,pairwise-distance matrix,Son and Baek dissimilarities,Son and Baek
Classifier: Development Status :: 5 - Production/Stable
Classifier: Intended Audience :: Science/Research
Classifier: License :: OSI Approved :: Apache Software License
Classifier: Natural Language :: English
Classifier: Programming Language :: Python :: 3 :: Only
Classifier: Programming Language :: Python :: 3.7
Classifier: Programming Language :: Python :: 3.8
Classifier: Programming Language :: Python :: 3.9
Classifier: Programming Language :: Python :: 3.10
Classifier: Programming Language :: Python :: 3.11
Classifier: Topic :: Scientific/Engineering :: Bio-Informatics
Classifier: Topic :: Scientific/Engineering :: Information Analysis
Requires-Python: >=3.7
License-File: LICENSE
License-File: AUTHORS.rst
Requires-Dist: numpy (>=1.21.4)
Requires-Dist: scipy (>=1.7.2)
